running.py
running-0.1.3.dist-info/LICENSE
running-0.1.3.dist-info/METADATA
running-0.1.3.dist-info/WHEEL
running-0.1.3.dist-info/entry_points.txt
running-0.1.3.dist-info/top_level.txt
running-0.1.3.dist-info/RECORD
