Metadata-Version: 2.1
Name: running
Version: 0.1.3
Summary: User-friendly running pace calculator
Home-page: https://github.com/jonathanlofgren/running
Author: Jonathan Löfgren
Author-email: lofgren021@gmail.com
Project-URL: Source, https://github.com/jonathanlofgren/running
Classifier: Natural Language :: English
Classifier: Programming Language :: Python :: 3.6
Classifier: Programming Language :: Python :: 3.7
Classifier: Programming Language :: Python :: 3.8
Classifier: Programming Language :: Python :: 3.9
Classifier: Programming Language :: Python :: 3.10
Classifier: License :: OSI Approved :: MIT License
License-File: LICENSE
